{
	"name": "DelimitedText3",
	"properties": {
		"linkedServiceName": {
			"referenceName": "SCCU_DataFactory_Storage",
			"type": "LinkedServiceReference"
		},
		"parameters": {
			"FolderPath": {
				"type": "string",
				"defaultValue": "@concat('offline-services/', item(), '/')"
			}
		},
		"annotations": [],
		"type": "DelimitedText",
		"typeProperties": {
			"location": {
				"type": "AzureBlobStorageLocation",
				"container": {
					"value": "@dataset().FolderPath",
					"type": "Expression"
				}
			},
			"columnDelimiter": ",",
			"escapeChar": "\\",
			"firstRowAsHeader": true,
			"quoteChar": "\""
		},
		"schema": []
	}
}